README.rst
setup.cfg
setup.py
cabot_alert_webhook/__init__.py
cabot_alert_webhook/models.py
cabot_alert_webhook.egg-info/PKG-INFO
cabot_alert_webhook.egg-info/SOURCES.txt
cabot_alert_webhook.egg-info/dependency_links.txt
cabot_alert_webhook.egg-info/pbr.json
cabot_alert_webhook.egg-info/top_level.txt
cabot_alert_webhook/migrations/0001_initial.py
cabot_alert_webhook/migrations/__init__.py