Metadata-Version: 1.1
Name: cabot-alert-webhook
Version: 0.1.0
Summary: A Webhook plugin for Cabot
Home-page: https://github.com/rockerbox/cabot-alert-webhook
Author: Rockerbox
Author-email: engineering@rockerbox.com
License: UNKNOWN
Download-URL: https://github.com/rockerbox/cabot-alert-webhook/tarball/master
Keywords: cabot,webhook,status check
Platform: UNKNOWN
